{
  "subjek": {
    "aku": "KataGanti",
    "kowe": "KataGanti",
    "bapak": "KataNama",
    "ibu": "KataNama",
    "budi": "KataNama",
    "siti": "KataNama",
    "adhik": "KataNama",
    "adhik-lanang": "KataNama",
    "ibu-guru": "KataNama",
    "bapak-tani": "KataNama",
    "mbak-siti": "KataNama",
    "mas-budi": "KataNama"
  },
  "predikat": {
    "mangan": "KataKerja",
    "nulis": "KataKerja",
    "turu": "KataKerja",
    "dolan": "KataKerja",
    "nyerat": "KataKerja",
    "teko": "KataKerja",
    "dolanan": "KataKerja",
    "lagi-mangan": "KataKerja",
    "arep-turu": "KataKerja",
    "wis-bali": "KataKerja",
    "lagi-sinau": "KataKerja"
  },
  "objek": {
    "sego": "KataBenda",
    "buku": "KataBenda",
    "layang": "KataBenda",
    "sayur": "KataBenda",
    "bal": "KataBenda",
    "sego-goreng": "KataBenda",
    "teh-panas": "KataBenda",
    "buku-gambar": "KataBenda",
    "layang-kabar": "KataBenda",
    "sayur-asem": "KataBenda"
  },
  "pelengkap": {
    "bal": "KataBenda",
    "sego": "KataBenda",
    "buku": "KataBenda",
    "anyar": "KataSifat",
    "enak": "KataSifat",
    "gede": "KataSifat",
    "resik": "KataSifat",
    "siji": "KataBilangan",
    "loro": "KataBilangan",
    "akeh": "KataBilangan",
    "sego-goreng": "KataBenda"
  },
  "keterangan": {
    "ing": "Preposisi",
    "menyang": "Preposisi",
    "saking": "Preposisi",
    "omah": "KataLokasi",
    "pasar": "KataLokasi",
    "sekolah": "KataLokasi",
    "latar": "KataLokasi",
    "wingi": "KetWaktu",
    "saiki": "KetWaktu",
    "esuk": "KetWaktu"
  }
}